BoundingBox.py
BoundingBoxes.py
MANIFEST.in
README.rst
detcivar.py
detmdreport.py
detmet.py
detutils.py
setup.py
detmetric.egg-info/PKG-INFO
detmetric.egg-info/SOURCES.txt
detmetric.egg-info/dependency_links.txt
detmetric.egg-info/requires.txt
detmetric.egg-info/top_level.txt
template/report.md
template/static/ap1.png
template/static/ap2.png
template/static/ap3.png
template/static/iou.png
template/static/prcurve1.png
template/static/prcurve2.png
template/static/prcurve3.png
template/static/prcurve4.png
template/static/predict_type.png
template/static/sample.png
template/static/table1.png
template/static/table2.png