Metadata-Version: 1.1
Name: detmetric
Version: 0.2.0
Summary: Object Detection Metric in Computer Vision
Home-page: https://github.com/DataXujing/detmetric
Author: Xu Jing
Author-email: 274762204@qq.com
License: MIT License
Keywords: object detection
Platform: linux/Windows
Classifier: Development Status :: 3 - Alpha
Classifier: Topic :: Text Processing
Classifier: License :: OSI Approved :: MIT License
Classifier: Programming Language :: Python :: 3
Classifier: Programming Language :: Python :: 3.5
Classifier: Programming Language :: Python :: 3.6
Classifier: Programming Language :: Python :: 3.7
Classifier: Programming Language :: Python :: 3.8
